gbd_mapping/__about__.py
gbd_mapping/__init__.py
gbd_mapping/_version.py
gbd_mapping/base_template.py
gbd_mapping/cause.py
gbd_mapping/cause_template.py
gbd_mapping/covariate.py
gbd_mapping/covariate_template.py
gbd_mapping/etiology.py
gbd_mapping/etiology_template.py
gbd_mapping/id.py
gbd_mapping/risk_factor.py
gbd_mapping/risk_factor_template.py
gbd_mapping/sequela.py
gbd_mapping/sequela_template.py
gbd_mapping-5.0.0.dist-info/licenses/AUTHORS.rst
gbd_mapping-5.0.0.dist-info/licenses/LICENSE.txt
gbd_mapping_generator/__init__.py
gbd_mapping_generator/base_template_builder.py
gbd_mapping_generator/build_mapping.py
gbd_mapping_generator/cause_builder.py
gbd_mapping_generator/covariate_builder.py
gbd_mapping_generator/data.py
gbd_mapping_generator/etiology_builder.py
gbd_mapping_generator/globals.py
gbd_mapping_generator/id_builder.py
gbd_mapping_generator/risk_builder.py
gbd_mapping_generator/sequela_builder.py
gbd_mapping_generator/util.py
gbd_mapping-5.0.0.dist-info/METADATA
gbd_mapping-5.0.0.dist-info/WHEEL
gbd_mapping-5.0.0.dist-info/entry_points.txt
gbd_mapping-5.0.0.dist-info/top_level.txt
gbd_mapping-5.0.0.dist-info/RECORD
