Metadata-Version: 2.4
Name: gbd_mapping
Version: 5.0.0
Summary: A programmatically accessible mapping of gbd entities.
Home-page: https://github.com/ihmeuw/gbd_mapping
Author: The vivarium developers
Author-email: vivarium.dev@gmail.com
License-File: LICENSE.txt
License-File: AUTHORS.rst
Requires-Dist: vivarium_dependencies[click,numpy,pandas]
Requires-Dist: vivarium_build_utils<3.0.0,>=2.0.0
Requires-Dist: pyyaml
Provides-Extra: docs
Requires-Dist: vivarium_dependencies[sphinx]; extra == "docs"
Provides-Extra: interactive
Requires-Dist: vivarium_dependencies[interactive]; extra == "interactive"
Provides-Extra: test
Requires-Dist: vivarium_dependencies[pytest]; extra == "test"
Provides-Extra: data
Requires-Dist: vivarium-gbd-access<6.0.0,>=5.0.0; extra == "data"
Provides-Extra: dev
Requires-Dist: vivarium_dependencies[sphinx]; extra == "dev"
Requires-Dist: vivarium_dependencies[interactive]; extra == "dev"
Requires-Dist: vivarium_dependencies[pytest]; extra == "dev"
Requires-Dist: vivarium-gbd-access<6.0.0,>=5.0.0; extra == "dev"
Requires-Dist: vivarium_dependencies[lint]; extra == "dev"
Dynamic: author
Dynamic: author-email
Dynamic: description
Dynamic: home-page
Dynamic: license-file
Dynamic: provides-extra
Dynamic: requires-dist
Dynamic: summary
